m1n1Exception/__init__.py
m1n1Exception/exceptions.py
m1n1Exception/functions.py
m1n1Exception-2.7.dist-info/LICENSE
m1n1Exception-2.7.dist-info/METADATA
m1n1Exception-2.7.dist-info/WHEEL
m1n1Exception-2.7.dist-info/top_level.txt
m1n1Exception-2.7.dist-info/RECORD
