Metadata-Version: 2.1
Name: m1n1Exception
Version: 2.7
Summary: Python library for conveniently handling errors
Home-page: https://github.com/Mini-Exploit/m1n1Exception
Author: MiniExploit
Author-email: miniexploitttt@gmail.com
Project-URL: Bug Tracker, https://github.com/Mini-Exploit/m1n1Exception/issues
Classifier: Programming Language :: Python :: 3
Classifier: License :: OSI Approved :: MIT License
Classifier: Operating System :: OS Independent
Requires-Python: >=3.6
License-File: LICENSE
